ensembletr/__init__.py
ensembletr/main.py
ensembletr/recordcluster.py
ensembletr/tests/__init__.py
ensembletr/tests/test_recordcluster.py
ensembletr/tests/test_utils.py
ensembletr/utils.py
ensembletr/vcfio.py
ensembletr/version.py
ensembletr-1.0.1.dist-info/METADATA
ensembletr-1.0.1.dist-info/WHEEL
ensembletr-1.0.1.dist-info/entry_points.txt
ensembletr-1.0.1.dist-info/RECORD
