Metadata-Version: 2.1
Name: EnsembleTR
Version: 1.0.1
Summary: Ensemble genotyping of tandem repeats
Home-page: https://github.com/gymrek-lab/EnsembleTR/tree/main
License: MIT
Author: Helyaneh Ziaei Jam
Requires-Python: >=3.8,<4.0
Classifier: License :: OSI Approved :: MIT License
Classifier: Programming Language :: Python :: 3
Classifier: Programming Language :: Python :: 3.8
Classifier: Programming Language :: Python :: 3.9
Classifier: Programming Language :: Python :: 3.10
Classifier: Programming Language :: Python :: 3.11
Classifier: Programming Language :: Python :: 3.12
Classifier: Programming Language :: Python :: 3.13
Requires-Dist: cyvcf2 (>=0.30.14)
Requires-Dist: networkx (>2.6.3)
Requires-Dist: numpy (>=1.22.0)
Requires-Dist: pyfaidx (>0.6.4)
Requires-Dist: trtools (>=4.2.1)
Project-URL: Repository, https://github.com/gymrek-lab/EnsembleTR/tree/main
